soxutils/__init__.py
soxutils/draw.py
soxutils/entry.py
soxutils/frame.py
worship-0.0.1.dist-info/LICENSE
worship-0.0.1.dist-info/METADATA
worship-0.0.1.dist-info/WHEEL
worship-0.0.1.dist-info/entry_points.txt
worship-0.0.1.dist-info/top_level.txt
worship-0.0.1.dist-info/RECORD
