Metadata-Version: 2.1
Name: worship
Version: 0.0.1
Summary: Sound processing toolkit with Python
Home-page: https://github.com/GaoangLiu/psox
Author: SLP
Author-email: byteleap@gmail.com
License: UNKNOWN
Platform: UNKNOWN
Classifier: Programming Language :: Python :: 3
Classifier: License :: OSI Approved :: MIT License
Classifier: Operating System :: OS Independent
Requires-Dist: smart-open
Requires-Dist: pydub
Requires-Dist: wave
Requires-Dist: librosa
